{
    "men":[
        "Aaron",
        "Dario",
        "Dominik",
        "Germain",
        "Marc",
        "Marcel",
        "Marko",
        "Marvin",
        "Maximilian",
        "Sascha"
    ],
    "women":[
        "Christin",
        "Jill",
        "Kathleen",
        "Laura",
        "Leonie",
        "Melissa",
        "Mirjam",
        "Sabrina",
        "Vanessa",
        "Victoria"        
    ],
    "additional_men":[
        
    ],
    "additional_women":[
        "VanessaM"
    ],
    "perfect_matches":[
        "Marcel+Leonie",
        "Aaron+Melissa",
        "Marc+Mirjam"
    ],
    "no_matches":[
        "Maximilian+Sabrina",
        "Aaron+Kathleen",
        "Marcel+Laura",
        "Marcel+Christin",
        "Marcel+Jill",
        "Marcel+Kathleen",
        "Marcel+Melissa",
        "Marcel+Mirjam",
        "Marcel+Sabrina",
        "Marcel+Vanessa",
        "Marcel+Victoria",
        "Marcel+VanessaM",
        "Aaron+Leonie",
        "Dario+Leonie",
        "Dominik+Leonie",
        "Germain+Leonie",
        "Marc+Leonie",
        "Marko+Leonie",
        "Marvin+Leonie",
        "Maximilian+Leonie",
        "Sascha+Leonie",
        "Dario+Laura",
        "Marko+Sabrina",
        "Aaron+Vanessa",
        "Dario+Victoria",
        "Dominik+Melissa",
        "Germain+Jill",
        "Marc+VanessaM",
        "Marko+Laura",
        "Marvin+Kathleen",
        "Maximilian+Mirjam",
        "Sascha+Sabrina",
        "Aaron+Christin",
        "Aaron+Jill",
        "Aaron+Laura",
        "Aaron+Mirjam",
        "Aaron+Sabrina",
        "Aaron+Victoria",
        "Dario+Melissa",
        "Germain+Melissa",
        "Marc+Melissa",
        "Marko+Melissa",
        "Marvin+Melissa",
        "Maximilian+Melissa",
        "Sascha+Melissa",
        "Marc+Christin",
        "Marc+Jill",
        "Marc+Kathleen",
        "Marc+Laura",
        "Marc+Sabrina",
        "Marc+Vanessa",
        "Marc+Victoria",
        "Dario+Mirjam",
        "Dominik+Mirjam",
        "Germain+Mirjam",
        "Marko+Mirjam",
        "Marvin+Mirjam",
        "Sascha+Mirjam"
    ],
    "matching_nights":{
        "1":{
            "pairs":[
                "Aaron+Kathleen",
                "Dario+Victoria",
                "Dominik+Melissa",
                "Germain+Leonie",
                "Marc+Mirjam",
                "Marcel+Laura",
                "Marko+Sabrina",
                "Marvin+Jill",
                "Maximilian+Christin",
                "Sascha+Vanessa"
            ],
            "spots":2
        },
        "2":{
            "pairs":[
                "Aaron+Kathleen",
                "Dario+Laura",
                "Dominik+Melissa",
                "Germain+Victoria",
                "Marc+Mirjam",
                "Marcel+Leonie",
                "Marko+Sabrina",
                "Marvin+Vanessa",
                "Maximilian+Christin",
                "Sascha+Jill"
            ],
            "spots":2
        },
        "3":{
            "pairs":[
                "Aaron+Melissa",
                "Dario+Victoria",
                "Dominik+Vanessa",
                "Germain+Christin",
                "Marc+Leonie",
                "Marcel+Laura",
                "Marko+Mirjam",
                "Marvin+Kathleen",
                "Maximilian+Jill",
                "Sascha+Sabrina"
            ],
            "spots":3
        },
        "4":{
            "pairs":[
                "Aaron+Melissa",
                "Dario+Kathleen",
                "Dominik+Laura",
                "Germain+Victoria",
                "Marc+Mirjam",
                "Marcel+Leonie",
                "Marko+Sabrina",
                "Marvin+Christin",
                "Maximilian+Jill",
                "Sascha+Vanessa"
            ],
            "spots":3
        },
        "5":{
            "pairs":[
                "Aaron+Mirjam",
                "Dario+Victoria",
                "Dominik+Vanessa",
                "Germain+Christin",
                "Marc+Melissa",
                "Marcel+Leonie",
                "Marko+VanessaM",
                "Marvin+Kathleen",
                "Maximilian+Laura",
                "Sascha+Jill"
            ],
            "spots":3
        },
        "6":{
            "pairs":[
                "Aaron+Melissa",
                "Dario+VanessaM",
                "Dominik+Vanessa",
                "Germain+Victoria",
                "Marc+Mirjam",
                "Marcel+Leonie",
                "Marko+Sabrina",
                "Marvin+Laura",
                "Maximilian+Christin",
                "Sascha+Jill"
            ],
            "spots":4
        },
        "7":{
            "pairs":[
                "Aaron+Melissa",
                "Dario+Sabrina",
                "Dominik+Laura",
                "Germain+VanessaM",
                "Marc+Mirjam",
                "Marcel+Leonie",
                "Marko+Victoria",
                "Marvin+Kathleen",
                "Maximilian+Christin",
                "Sascha+Jill"
            ],
            "spots":4
        },
        "8":{
            "pairs":[
                "Aaron+Vanessa",
                "Dario+Victoria",
                "Dominik+Melissa",
                "Germain+Jill",
                "Marc+VanessaM",
                "Marcel+Leonie",
                "Marko+Laura",
                "Marvin+Kathleen",
                "Maximilian+Mirjam",
                "Sascha+Sabrina"
            ],
            "spots":1
        },
        "9":{
            "pairs":[
                "Aaron+Melissa",
                "Dario+Kathleen",
                "Dominik+Sabrina",
                "Germain+Laura",
                "Marc+Mirjam",
                "Marcel+Leonie",
                "Marko+Victoria",
                "Marvin+Vanessa",
                "Maximilian+Christin",
                "Sascha+Jill"
            ],
            "spots":3
        },
        "10":{
            "pairs":[
                "Aaron+Melissa",
                "Dario+Sabrina",
                "Dominik+Vanessa",
                "Germain+Christin",
                "Marc+Mirjam",
                "Marcel+Leonie",
                "Marko+Kathleen",
                "Marvin+Jill",
                "Maximilian+Victoria",
                "Sascha+Laura"
            ],
            "spots":10
        }
    }
}